dicksonui/Application.py
dicksonui/Control.py
dicksonui/DicksonUI.js
dicksonui/__init__.py
dicksonui/bom.py
dicksonui/dom.py
dicksonui/fakeattr.py
dicksonui/index.html
dicksonui/wsocket.py
DicksonUI_Micro-2.0.0.dist-info/LICENSE
DicksonUI_Micro-2.0.0.dist-info/METADATA
DicksonUI_Micro-2.0.0.dist-info/WHEEL
DicksonUI_Micro-2.0.0.dist-info/top_level.txt
DicksonUI_Micro-2.0.0.dist-info/zip-safe
DicksonUI_Micro-2.0.0.dist-info/RECORD
