Metadata-Version: 2.1
Name: DicksonUI-Micro
Version: 2.0.0
Summary: Lightweight And Full Featured Browser Based UI / GUI (Graphical User Interface Library)
Home-page: https://github.com/Ksengine/DicksonUI
Author: Kavindu Santhusa
Author-email: kavindusanthusa@gmail.com
License: MIT
Download-URL: https://pypi.python.org/pypi/DicksonUI
Keywords: python,gui,html,css,js,javascript,ui,servelight,server,user-interface,graphical-user-interface,lightweight,full-featured,browser,browser-based,webview,html,view,remote,interface
Platform: any
Classifier: License :: OSI Approved :: MIT License
Classifier: Intended Audience :: Developers
Classifier: Development Status :: 5 - Production/Stable
Classifier: Operating System :: OS Independent
Classifier: Operating System :: MacOS :: MacOS X
Classifier: Operating System :: Microsoft :: Windows
Classifier: Operating System :: POSIX
Classifier: Programming Language :: Python
Classifier: Programming Language :: Python :: 2
Classifier: Programming Language :: Python :: 2.7
Classifier: Programming Language :: Python :: 3.4
Classifier: Programming Language :: Python :: 3.5
Classifier: Programming Language :: Python :: 3.6
Classifier: Programming Language :: Python :: 3.7
Classifier: Programming Language :: Python :: 3
Classifier: Programming Language :: Python :: 3.5
Classifier: Programming Language :: Python :: 3.7
Classifier: Programming Language :: Python :: 3.8
